totalface/__init__.py
totalface/bbox_anchor.py
totalface/get_config.py
totalface/print_info.py
totalface/data/__init__.py
totalface/data/constant.py
totalface/data/image.py
totalface/data/experiments/__init__.py
totalface/data/experiments/AFLW/__init__.py
totalface/data/experiments/AFLW/pip_32_16_60_r18_l2_l1_10_1_nb10.py
totalface/data/experiments/COFW/__init__.py
totalface/data/experiments/COFW/pip_32_16_60_r18_l2_l1_10_1_nb10.py
totalface/data/experiments/WFLW/__init__.py
totalface/data/experiments/WFLW/pip_32_16_60_mv3_large_l2_l1_10_1_nb10.py
totalface/data/experiments/WFLW/pip_32_16_60_mv3_small_l2_l1_10_1_nb10.py
totalface/data/experiments/WFLW/pip_32_16_60_r18_l2_l1_10_1_nb10.py
totalface/data/experiments/data_300W/__init__.py
totalface/data/experiments/data_300W/pip_32_16_60_r18_l2_l1_10_1_nb10.py
totalface/eval/__init__.py
totalface/eval/commands/__init__.py
totalface/eval/commands/eval_ijbc.py
totalface/eval/commands/eval_megaface.py
totalface/eval/commands/eval_verification.py
totalface/eval/commands/run.py
totalface/eval/ijbc/__init__.py
totalface/eval/ijbc/eval_ijbc.py
totalface/eval/ijbc/ijbc_run.py
totalface/eval/megaface/__init__.py
totalface/eval/megaface/gen_features_lst.py
totalface/eval/megaface/interpolation.py
totalface/eval/megaface/megaface_results.py
totalface/eval/megaface/megaface_run.py
totalface/eval/megaface/remove_noises.py
totalface/eval/megaface/run_experiment.py
totalface/eval/verification/__init__.py
totalface/eval/verification/verification.py
totalface/eval/verification/eval_util/__init__.py
totalface/eval/verification/eval_util/verification.py
totalface/eval/verification/eval_util/verification_g.py
totalface/eval/verification/eval_util/verification_m.py
totalface/face/__init__.py
totalface/face/blur.py
totalface/face/common.py
totalface/face/get_result.py
totalface/model_zoo/__init__.py
totalface/model_zoo/get_models.py
totalface/model_zoo/backbones/__init__.py
totalface/model_zoo/backbones/efficientNet.py
totalface-0.0.1.dist-info/METADATA
totalface-0.0.1.dist-info/WHEEL
totalface-0.0.1.dist-info/top_level.txt
totalface-0.0.1.dist-info/RECORD
